roboidai/__init__.py
roboidai/_camera.py
roboidai/_keyevent.py
roboidai/_window.py
roboidai/_image/__init__.py
roboidai/_image/_age_gender.py
roboidai/_image/_aruco_detector.py
roboidai/_image/_body_pose.py
roboidai/_image/_body_segmentation.py
roboidai/_image/_color_detector.py
roboidai/_image/_expression.py
roboidai/_image/_face_detector.py
roboidai/_image/_face_marker.py
roboidai/_image/_face_mesh.py
roboidai/_image/_hand_pose.py
roboidai/_image/_object_detector.py
roboidai/_image/_tool.py
roboidai/_image/_util.py
roboidai/_image/malgun.ttf
roboidai/_lang/__init__.py
roboidai/_lang/_translator.py
roboidai/_ml/__init__.py
roboidai/_ml/_knn.py
roboidai/_ml/_linear_regression.py
roboidai/_model/blazeface.h5
roboidai/_model/object_labels.txt
roboidai/_navi/__init__.py
roboidai/_navi/_cam_racer.py
roboidai/_navi/_simple_cam_racer.py
roboidai/_tm/__init__.py
roboidai/_tm/_image.py
roboidai/lab/__init__.py
roboidai/lab/_fruit_detector.py
roboidai/lab/_image.py
roboidai/lab/_line_recorder.py
roboidai/lab/_line_tracer.py
roboidai/lab/_q_world.py
roboidai/lab/_track.py
roboidai/lab/_tree.py
roboidai/lab/_zoo.py
roboidai/lab/ko/__init__.py
roboidai/util/__init__.py
roboidai/util/_key.py
roboidai-1.1.23.dist-info/LICENSE
roboidai-1.1.23.dist-info/METADATA
roboidai-1.1.23.dist-info/WHEEL
roboidai-1.1.23.dist-info/top_level.txt
roboidai-1.1.23.dist-info/RECORD
