Metadata-Version: 2.1
Name: roboidai
Version: 1.1.23
Summary: Python Package for Roboid AI
Author: Kwang-Hyun Park
Author-email: akaii@kw.ac.kr
Classifier: License :: OSI Approved :: GNU Lesser General Public License v2 or later (LGPLv2+)
Requires-Python: >=3
License-File: LICENSE
Requires-Dist: roboid
Requires-Dist: ifaddr
Requires-Dist: pyttsx3
Requires-Dist: pynput
Requires-Dist: pandas
Requires-Dist: matplotlib
Requires-Dist: scikit-learn
Requires-Dist: numpy
Requires-Dist: mediapipe
Requires-Dist: fer
Requires-Dist: opencv-python
Requires-Dist: tensorflow
Requires-Dist: tf-keras
